publish.py
publish-0.3.6.dist-info/LICENSE
publish-0.3.6.dist-info/METADATA
publish-0.3.6.dist-info/WHEEL
publish-0.3.6.dist-info/entry_points.txt
publish-0.3.6.dist-info/top_level.txt
publish-0.3.6.dist-info/zip-safe
publish-0.3.6.dist-info/RECORD
