Metadata-Version: 2.1
Name: publish
Version: 0.3.6
Summary: Publish python package to PyPI and Github
Home-page: https://github.com/fiaas/publish
Author: FiaaS developers
Author-email: fiaas@googlegroups.com
License: Apache License
Keywords: pypi github fiaas
Classifier: Development Status :: 3 - Alpha
Classifier: Intended Audience :: Developers
Classifier: License :: OSI Approved :: Apache Software License
Classifier: Operating System :: OS Independent
Classifier: Programming Language :: Python
Classifier: Programming Language :: Python :: 3
Classifier: Programming Language :: Python :: 3.9
Classifier: Topic :: Internet
Classifier: Topic :: Software Development :: Build Tools
Classifier: Topic :: System :: Software Distribution
License-File: LICENSE
Requires-Dist: GitPython ==3.1.41
Requires-Dist: twine ==5.1.1
Requires-Dist: githubrelease ==1.5.9
Provides-Extra: codacy
Requires-Dist: codacy-coverage ; extra == 'codacy'
Provides-Extra: dev
Requires-Dist: tox ==4.12.0 ; extra == 'dev'
Requires-Dist: pytest ==7.4.4 ; extra == 'dev'
Requires-Dist: pytest-cov ==4.1.0 ; extra == 'dev'
Requires-Dist: pytest-html ==4.1.1 ; extra == 'dev'
Requires-Dist: pytest-sugar ==0.9.7 ; extra == 'dev'
Requires-Dist: prospector ==1.10.3 ; extra == 'dev'
Provides-Extra: docs
Requires-Dist: Sphinx >=1.6.3 ; extra == 'docs'
